codecombine/__about__.py
codecombine/__init__.py
codecombine/cli.py
codecombine/core.py
codecombine-0.0.1.dist-info/METADATA
codecombine-0.0.1.dist-info/WHEEL
codecombine-0.0.1.dist-info/entry_points.txt
codecombine-0.0.1.dist-info/RECORD
