Metadata-Version: 2.3
Name: codecombine
Version: 0.0.1
Summary: A utility for combining code files from a directory structure into consolidated text files
Project-URL: Homepage, https://github.com/michaelmendoza/codecombine
Project-URL: Bug Tracker, https://github.com/michaelmendoza/codecombine/issues
Author-email: Michael Mendoza <askmichaelmendoza@gmail.com>
License-Expression: MIT
Keywords: ChatGPT tool,code,combine,development,productivity,utility
Classifier: License :: OSI Approved :: MIT License
Classifier: Programming Language :: Python :: 3
Requires-Python: >=3.6
